{
  "supplierName": "METRO",
  "date": "2023-06-28",
  "invoiceNo": "113/599",
  "totalAmount": 1940.9,
  "items": [
    {
      "name": "MP RACLET PLAN DE TRAV 25CM",
      "quantity": 1.0,
      "unit": "U",
      "unitPrice": 13.72,
      "totalPrice": 13.72
    },
    {
      "name": "MP TAB SERV NOIRZIP MULTIPOCH",
      "quantity": 2.0,
      "unit": "U",
      "unitPrice": 16.62,
      "totalPrice": 33.24
    },
    {
      "name": "MP 2 TABLIERS MULTIPOCHE NOIR",
      "quantity": 2.0,
      "unit": "U",
      "unitPrice": 20.77,
      "totalPrice": 41.54
    },
    {
      "name": "ESSOREUSE 10L MANUEL DYNAMIC",
      "quantity": 1.0,
      "unit": "L",
      "unitPrice": 93.6,
      "totalPrice": 93.6
    },
    {
      "name": "10CPELLE MONNAI NOIR POLYPRO",
      "quantity": 2.0,
      "unit": "U",
      "unitPrice": 16.67,
      "totalPrice": 33.34
    },
    {
      "name": "PIQUE FICHE SOCLE MARBRE",
      "quantity": 2.0,
      "unit": "U",
      "unitPrice": 15.59,
      "totalPrice": 31.18
    },
    {
      "name": "R134A MACH GLACONS B 4015 AS",
      "quantity": 1.0,
      "unit": "U",
      "unitPrice": 1301.0,
      "totalPrice": 1301.0
    },
    {
      "name": "PORTE VISUEL VERTICAL A4 PLEXI",
      "quantity": 10.0,
      "unit": "U",
      "unitPrice": 6.98,
      "totalPrice": 69.8
    }
  ]
}